tkasegui/__init__.py
tkasegui/__main__.py
tkasegui/main.py
tkasegui/geometry/__init__.py
tkasegui/geometry/prdf.py
tkasegui/gui/__init__.py
tkasegui/gui/add.py
tkasegui/gui/ag.py
tkasegui/gui/bonds.py
tkasegui/gui/calculator.py
tkasegui/gui/celleditor.py
tkasegui/gui/colors.py
tkasegui/gui/constraints.py
tkasegui/gui/defaults.py
tkasegui/gui/dynamics.py
tkasegui/gui/energyforces.py
tkasegui/gui/graphs.py
tkasegui/gui/gui.py
tkasegui/gui/images.py
tkasegui/gui/minimize.py
tkasegui/gui/modify.py
tkasegui/gui/movie.py
tkasegui/gui/nanoparticle.py
tkasegui/gui/nanotube.py
tkasegui/gui/pipe.py
tkasegui/gui/quickinfo.py
tkasegui/gui/rdf.py
tkasegui/gui/render.py
tkasegui/gui/repeat.py
tkasegui/gui/rotate.py
tkasegui/gui/save.py
tkasegui/gui/settings.py
tkasegui/gui/simulation.py
tkasegui/gui/status.py
tkasegui/gui/surfaceslab.py
tkasegui/gui/ui.py
tkasegui/gui/utils.py
tkasegui/gui/view.py
tkasegui/gui/widgets.py
tkasegui-0.5.dist-info/LICENSE
tkasegui-0.5.dist-info/METADATA
tkasegui-0.5.dist-info/WHEEL
tkasegui-0.5.dist-info/top_level.txt
tkasegui-0.5.dist-info/RECORD
