Metadata-Version: 2.1
Name: tkasegui
Version: 0.5
Summary: Unofficial ASE gui extension
Home-page: https://gitlab.com/Avakyan/tkasegui
Author: Leon Avakyan
Author-email: laavakyan@sfedu.ru
License: GPLv3
Classifier: Programming Language :: Python :: 3
Classifier: License :: OSI Approved :: GNU General Public License v3 (GPLv3)
Classifier: Operating System :: OS Independent
Requires-Python: >=3.8
License-File: LICENSE
Requires-Dist: ase
